wisdoms/__init__.py
wisdoms/archives.py
wisdoms/auth.py
wisdoms/config.py
wisdoms/es_db.py
wisdoms/es_model.py
wisdoms/exec.py
wisdoms/logger.py
wisdoms/ms.py
wisdoms/pg_db.py
wisdoms/utils.py
wisdoms/commons/__init__.py
wisdoms/commons/my_code.py
wisdoms/dapr/__init__.py
wisdoms/dapr/dapr.py
wisdoms-2.6.4.dist-info/LICENSE
wisdoms-2.6.4.dist-info/METADATA
wisdoms-2.6.4.dist-info/WHEEL
wisdoms-2.6.4.dist-info/top_level.txt
wisdoms-2.6.4.dist-info/RECORD
