Metadata-Version: 2.1
Name: wisdoms
Version: 2.6.4
Summary: fix dapr invoke function
Home-page: https://gitlab.com/soft-project/wisdom-lib
Author: tzxd group
Author-email: whosqays@qq.com
License: UNKNOWN
Platform: UNKNOWN
Classifier: Programming Language :: Python :: 3
Classifier: License :: OSI Approved :: MIT License
Classifier: Operating System :: OS Independent
Requires-Dist: pyYaml
